{
  "posts": [
    {
      "slug": "choosing-perfect-domain",
      "language": "en",
      "dateCreated": "2026-05-20",
      "dateUpdated": "2026-05-20"
    },
    {
      "slug": "como-escolher-dominio-perfeito",
      "language": "pt",
      "dateCreated": "2026-05-20",
      "dateUpdated": "2026-05-20"
    },
    {
      "slug": "small-business-website-cost",
      "language": "en",
      "dateCreated": "2026-05-20",
      "dateUpdated": "2026-05-20"
    },
    {
      "slug": "quanto-custa-website-pequena-empresa",
      "language": "pt",
      "dateCreated": "2026-05-20",
      "dateUpdated": "2026-05-20"
    },
    {
      "slug": "need-website-if-have-instagram",
      "language": "en",
      "dateCreated": "2026-05-20",
      "dateUpdated": "2026-05-20"
    },
    {
      "slug": "precisa-website-se-tem-instagram",
      "language": "pt",
      "dateCreated": "2026-05-20",
      "dateUpdated": "2026-05-20"
    },
    {
      "slug": "local-seo-checklist-small-business",
      "language": "en",
      "dateCreated": "2026-05-20",
      "dateUpdated": "2026-05-20"
    },
    {
      "slug": "checklist-seo-local-pequenos-negocios",
      "language": "pt",
      "dateCreated": "2026-05-20",
      "dateUpdated": "2026-05-20"
    }
  ],
  "lastUpdated": "2026-05-20T11:36:00Z"
}
