{
  "slug": "when-to-redesign-small-business-website",
  "language": "en",
  "title": "When to Redesign Your Small Business Website",
  "description": "Signs you need a small business website redesign: outdated design, mobile issues, poor SEO, slow speed, and how to plan a refresh without downtime.",
  "author": "InfoWeb",
  "dateCreated": "2026-05-27",
  "dateUpdated": "2026-05-27",
  "category": "web-design",
  "tags": [
    "website redesign small business",
    "when to redesign website",
    "refresh business website"
  ],
  "image": "./assets/featured.png",
  "imageAlt": "Before and after website redesign mockups for a small business on a designer screen",
  "readTime": 7,
  "featured": false,
  "published": true,
  "alternateLanguage": {
    "pt": "quando-redesenhar-website-pequeno-negocio"
  }
}
